mpldock/__init__.py
mpldock/backend.py
mpldock/common.py
mpldock/figure.py
mpldock/statemanager.py
mpldock/tweaks.py
mpldock/window.py
mpldock/windows.py
mpldock-0.2.dist-info/licenses/LICENSE
mpldock-0.2.dist-info/METADATA
mpldock-0.2.dist-info/WHEEL
mpldock-0.2.dist-info/top_level.txt
mpldock-0.2.dist-info/RECORD
