Metadata-Version: 2.4
Name: mpldock
Version: 0.2
Summary: Dock matplotlib figures and other widgets. Preserve layout between sessions.
Home-page: https://github.com/peper0/mpldock
Author: Tomasz Łakota
Author-email: tomasz.lakota@gmail.com
License: MIT
Keywords: matplotlib,qt5,backend,dock,docking,dockable,layout
Classifier: Development Status :: 2 - Pre-Alpha
Classifier: License :: OSI Approved :: MIT License
Classifier: Programming Language :: Python :: 3.6
Classifier: Programming Language :: Python :: 3.7
Classifier: Programming Language :: Python :: 3.8
Classifier: Programming Language :: Python :: 3.9
Classifier: Programming Language :: Python :: 3.10
Classifier: Intended Audience :: Developers
Classifier: Intended Audience :: Science/Research
Classifier: Operating System :: OS Independent
Classifier: Topic :: Software Development
Classifier: Topic :: Software Development :: Libraries :: Python Modules
Requires-Python: >=3.6
License-File: LICENSE
Requires-Dist: PyQt5
Requires-Dist: matplotlib
Requires-Dist: appdirs
Provides-Extra: pyqtgraph
Requires-Dist: pyqtgraph; extra == "pyqtgraph"
Dynamic: author
Dynamic: author-email
Dynamic: classifier
Dynamic: description
Dynamic: description-content-type
Dynamic: home-page
Dynamic: keywords
Dynamic: license
Dynamic: license-file
Dynamic: provides-extra
Dynamic: requires-dist
Dynamic: requires-python
Dynamic: summary
